easybot/__init__.py
easybot/bot.py
easybot_telegram-0.1.0.dist-info/LICENSE
easybot_telegram-0.1.0.dist-info/METADATA
easybot_telegram-0.1.0.dist-info/WHEEL
easybot_telegram-0.1.0.dist-info/top_level.txt
easybot_telegram-0.1.0.dist-info/RECORD
