Metadata-Version: 2.2
Name: easybot-telegram
Version: 0.1.0
Summary: лучшая и простая библиотека для Telegram ботов
Home-page: 
Author: sinx
Author-email: sinx@rommiui.com
Classifier: Programming Language :: Python :: 3
Classifier: License :: OSI Approved :: MIT License
Classifier: Operating System :: OS Independent
Requires-Python: >=3.6
License-File: LICENSE
Requires-Dist: requests>=2.25.0
Dynamic: author
Dynamic: author-email
Dynamic: classifier
Dynamic: description
Dynamic: description-content-type
Dynamic: requires-dist
Dynamic: requires-python
Dynamic: summary
